djeveric/__init__.py
djeveric/emails.py
djeveric/fields.py
djeveric/models.py
djeveric/serializers.py
djeveric/tokens.py
djeveric/views.py
djeveric-0.2.0.dist-info/METADATA
djeveric-0.2.0.dist-info/WHEEL
djeveric-0.2.0.dist-info/top_level.txt
djeveric-0.2.0.dist-info/RECORD
