Metadata-Version: 2.1
Name: djeveric
Version: 0.2.0
Summary: Simple email confirmation for django model instances.
Home-page: https://git.hack-hro.de/memoorje/djeveric
Author: memoorje developers
Author-email: tach@memoorje.org
License: MIT
Platform: UNKNOWN
Classifier: Development Status :: 3 - Alpha
Classifier: License :: OSI Approved :: MIT License
Classifier: Programming Language :: Python
Classifier: Programming Language :: Python :: 3 :: Only
Requires-Dist: django (~=3.2.7)
Requires-Dist: djangorestframework (~=3.12.1)
